mutlycusm/__init__.py
mutlycusm-0.0.1.dist-info/LICENSE.txt
mutlycusm-0.0.1.dist-info/METADATA
mutlycusm-0.0.1.dist-info/WHEEL
mutlycusm-0.0.1.dist-info/top_level.txt
mutlycusm-0.0.1.dist-info/RECORD
