Metadata-Version: 2.1
Name: mutlycusm
Version: 0.0.1
Summary: 调用此方法可打印9*9乘法表
Author: 雒国林
Author-email: 1348102133@qq.com
License: UNKNOWN
Platform: UNKNOWN
Classifier: Programming Language :: Python :: 3
Classifier: License :: OSI Approved :: MIT License
Classifier: Operating System :: OS Independent
Requires-Python: >=3.7
License-File: LICENSE.txt
